llm_jina_reader.py
llm_jina_reader-2025.4.3.dist-info/licenses/LICENSE
llm_jina_reader-2025.4.3.dist-info/METADATA
llm_jina_reader-2025.4.3.dist-info/WHEEL
llm_jina_reader-2025.4.3.dist-info/entry_points.txt
llm_jina_reader-2025.4.3.dist-info/top_level.txt
llm_jina_reader-2025.4.3.dist-info/RECORD
