Metadata-Version: 2.4
Name: llm-jina-reader
Version: 2025.4.3
Summary: LLM plugin for pulling content from Jina Reader API
Author: Jeff Triplett
License-Expression: Apache-2.0
Project-URL: Homepage, https://github.com/jefftriplett/llm-jina-reader
Project-URL: Changelog, https://github.com/jefftriplett/llm-jina-reader/releases
Project-URL: Issues, https://github.com/jefftriplett/llm-jina-reader/issues
Project-URL: CI, https://github.com/jefftriplett/llm-jina-reader/actions
Requires-Python: >=3.9
License-File: LICENSE
Requires-Dist: llm>=0.24
Requires-Dist: httpx
Provides-Extra: test
Requires-Dist: pytest; extra == "test"
Requires-Dist: pytest-httpx; extra == "test"
Dynamic: license-file
